[
  {
    "name": "סתיו שפיר",
    "quote": "אם עושים הצבעות על אוטומט אפשר לשים פה מכונה של חברי כנסת, לא צריך להצביע."
  },
  {
    "name": "יולי אדלשטיין",
    "quote": "אתה הצבעת? אתה לחצת על הכפתור?"
  },
  {
    "name": "אלי אלאלוף",
    "quote": "ברשותכם, נצביע. מי בעד החוק? מי נגד?"
  },
  {
    "name": "יואב סגלוביץ'",
    "quote": "אבל התפקיד שלנו להוציא חוקים טובים, לא חוקים גרועים פחות. אתם עושים אידיאולוגיה מתקלה. מה קרה לכם? השתגעתם?"
  },
  {
    "name": "קארין אלהרר",
    "quote": "למה לחוקק חוקים בכנסת? גם כך אף אחד לא שם עליהם, אפילו לא המדינה."
  },
  {
    "name": "יואב קיש",
    "quote": "איך אומר יואל חסון? מכונת הצבעות."
  },
  {
    "name": "אחמד טיבי",
    "quote": "תלונות מביאות להצעות חוק. הן גורמות לחברי כנסת לחוקק חוקים"
  },
  {
    "name": "מיכל בירן",
    "quote": "לדעתי אפילו הארכת חופשת לידה התקבלה נגד משמעת קואליציונית."
  },
  {
    "name": "תמר זנדברג",
    "quote": "אז התקפלתם בגלל משמעת קואליציונית? זה מה שאתה אומר? איזה מין תירוץ זה?"
  },
  {
    "name": "מכלוף מיקי זוהר",
    "quote": "אז תצביע נגד ותמשיך להיות שמונה מנדטים."
  },
  {
    "name": "מיקי לוי",
    "quote": "למה אישרתם, למה הצבעתם בעד? תצביעו נגד. תצביעו נגד."
  },
  {
    "name": "אורן אסף חזן",
    "quote": "אם קנו פה הצבעות בכסף, אני רוצה לדעת על זה."
  }
]
